hum/__init__.py
hum/extra_util.py
hum/pyo_synths.py
hum/pyo_util.py
hum/pyo_util_examples.py
hum/synth_funcs.py
hum/util.py
hum/examples/__init__.py
hum/examples/keyboard_control.py
hum/examples/pyo_util_examples.py
hum/scrap/__init__.py
hum/scrap/belangeo_Degradation.py
hum/utils/__init__.py
hum/utils/date_ticks.py
hum/utils/plotting.py
hum-1.0.12.dist-info/licenses/LICENSE
hum-1.0.12.dist-info/METADATA
hum-1.0.12.dist-info/WHEEL
hum-1.0.12.dist-info/top_level.txt
hum-1.0.12.dist-info/RECORD
