Metadata-Version: 2.4
Name: hum
Version: 1.0.12
Summary: A python synthesizer for creating and manipulating audio signals.
Home-page: https://github.com/thorwhalen/hum
License: mit
Keywords: signal processing,audio generation,data,synthesizer,sonification
Platform: any
License-File: LICENSE
Requires-Dist: IPython
Requires-Dist: matplotlib
Requires-Dist: numpy
Requires-Dist: recode
Requires-Dist: pyo
Requires-Dist: scipy
Requires-Dist: tonal
Provides-Extra: testing
Dynamic: description
Dynamic: description-content-type
Dynamic: license-file
